mkeima/__init__.py
mkeima/analyze.py
mkeima/plot.py
mkeima/read.py
mkeima-0.6.0.dist-info/LICENSE.txt
mkeima-0.6.0.dist-info/METADATA
mkeima-0.6.0.dist-info/WHEEL
mkeima-0.6.0.dist-info/top_level.txt
mkeima-0.6.0.dist-info/RECORD
