Metadata-Version: 2.1
Name: mkeima
Version: 0.6.0
Summary: Analysis of flow cytometry-based mKeima assays in Python
Author-email: "David M. Hollenstein" <hollenstein.david@gmail.com>
License: Apache-2.0
Keywords: mkeima,flow cytometry,data analysis
Classifier: Development Status :: 3 - Alpha
Classifier: License :: OSI Approved :: Apache Software License
Classifier: Programming Language :: Python :: 3.9
Classifier: Topic :: Scientific/Engineering :: Bio-Informatics
Requires-Python: >=3.9
License-File: LICENSE.txt
Requires-Dist: matplotlib >=3.4
Requires-Dist: numpy >=1.20
Requires-Dist: pandas >=1.4
Requires-Dist: seaborn >=0.11
